LICENSE
antsichaut/__init__.py
antsichaut/antsichaut.py
antsichaut-0.4.0.dist-info/LICENSE
antsichaut-0.4.0.dist-info/METADATA
antsichaut-0.4.0.dist-info/WHEEL
antsichaut-0.4.0.dist-info/entry_points.txt
antsichaut-0.4.0.dist-info/RECORD
