Metadata-Version: 2.1
Name: antsichaut
Version: 0.4.0
Summary: antsichaut automates ansible changelog generation from GitHub Pull Requests
Home-page: https://github.com/rndmh3ro/antsichaut
License: MIT
Keywords: antsibull-changelog,release,ansible
Author: Sebastian Gumprich
Author-email: sebastian.gumprich@t-systems.com
Requires-Python: >=3.8,<4.0
Classifier: Development Status :: 3 - Alpha
Classifier: Environment :: Console
Classifier: Framework :: Ansible
Classifier: Intended Audience :: Developers
Classifier: License :: OSI Approved :: MIT License
Classifier: Programming Language :: Python :: 3
Classifier: Programming Language :: Python :: 3.8
Classifier: Programming Language :: Python :: 3.9
Classifier: Programming Language :: Python :: 3.10
Classifier: Programming Language :: Python :: 3.11
Classifier: Programming Language :: Python :: 3.12
Classifier: Topic :: Software Development :: Documentation
Requires-Dist: ConfigArgParse (>=1.4.1,<2.0.0)
Requires-Dist: requests (>=2.25.1,<3.0.0)
Requires-Dist: ruamel.yaml (>=0.17.9,<0.18.0)
Requires-Dist: single-source (>=0.3.0,<0.4.0)
Project-URL: Repository, https://github.com/rndmh3ro/antsichaut
